etltable/__init__.py
etltable/etltable.py
etltable/updatetable.py
etltable-0.0.1.dist-info/DESCRIPTION.rst
etltable-0.0.1.dist-info/METADATA
etltable-0.0.1.dist-info/RECORD
etltable-0.0.1.dist-info/WHEEL
etltable-0.0.1.dist-info/metadata.json
etltable-0.0.1.dist-info/top_level.txt
